{
  "31_44": {
    "title": "Beorn's House",
    "type": "site",
    "block": "hobbit",
    "site": 4,
    "cost": 4,
    "effects": {
      "type": "activated",
      "phase": "fellowship",
      "cost": {
        "type": "choice",
        "texts": [
          "Spot a GANDALF staff",
          "Play a GANDALF staff from your draw deck"
        ],
        "effects": [
          {
            "type": "spot",
            "filter": "choose(culture(gandalf),staff)"
          },
          {
            "type": "playCardFromDrawDeck",
            "filter": "choose(culture(gandalf),staff)"
          }
        ]
      },
      "effect": [
        {
          "type": "spot",
          "text": "Choose a Gandalf",
          "filter": "choose(name(Gandalf))",
          "memorize": "chosenGandalf"
        },
        {
          "type": "addModifier",
          "modifier": {
            "type": "cantBeDiscarded",
            "filter": "memory(chosenGandalf)"
          },
          "until": "endOfTurn"
        }
      ]
    }
  },
  "31_45": {
    "title": "Underground Lake",
    "cost": 2,
    "type": "site",
    "block": "hobbit",
    "site": 4,
    "keyword": [
      "underground",
      "river"
    ],
    "effects": {
      "type": "activated",
      "phase": "maneuver",
      "condition": {
        "type": "perPhaseLimit",
        "limit": 1,
        "perPlayer": true
      },
      "cost": {
        "type": "incrementPerPhaseLimit",
        "limit": 1,
        "perPlayer": true
      },
      "effect": {
        "type": "playCardFromDrawDeck",
        "filter": "choose(or(and(side(shadow),condition),name(The One Ring)))"
      }
    }
  },
  "31_46": {
    "title": "Forest River",
    "type": "site",
    "block": "hobbit",
    "site": 5,
    "cost": 7,
    "keyword": [
      "forest",
      "river"
    ],
    "effects": {
      "type": "activated",
      "phase": "assignment",
      "cost": {
        "type": "exert",
        "filter": "choose(your,orc)"
      },
      "effect": {
        "type": "cantBeAssignedToSkirmish",
        "filter": "choose(or(name(Gandalf),and(culture(elven),ally)))"
      }
    }
  },
  "31_47": {
    "title": "Thrór's Throne",
    "type": "site",
    "block": "hobbit",
    "site": 9,
    "cost": 9,
    "keyword": [
      "mountain",
      "underground"
    ],
    "effects": {
      "type": "modifier",
      "modifier": {
        "type": "modifyCost",
        "filter": "minion",
        "condition": {
          "type": "cantSpot",
          "filter": "culture(dwarven),name(The Arkenstone)"
        },
        "amount": -1
      }
    }
  }
}
