{
  "2_108": {
    "side": "free_people",
    "twilight": 1,
    "strength": 1,
    "culture": "Shire",
    "title": "*O Elbereth! Gilthoniel!",
    "type": "condition",
    "keyword": "Tale"
  },
  "2_109": {
    "side": "free_people",
    "twilight": 0,
    "culture": "Shire",
    "title": "Orc-bane",
    "type": "event",
    "keyword": "Maneuver"
  },
  "2_104": {
    "side": "free_people",
    "twilight": 1,
    "race": "Hobbit",
    "strength": 3,
    "culture": "Shire",
    "vitality": 4,
    "subtitle": "Horticulturalist",
    "signet": "gandalf",
    "title": "*Merry",
    "type": "companion",
    "resistance": 6
  },
  "2_105": {
    "side": "free_people",
    "twilight": 2,
    "culture": "Shire",
    "itemclass": "Armor",
    "title": "*Mithril-coat",
    "type": "artifact"
  },
  "2_106": {
    "side": "free_people",
    "twilight": 1,
    "culture": "Shire",
    "title": "Nice Imitation",
    "type": "condition",
    "keyword": [
      "Support Area",
      "Stealth"
    ]
  },
  "2_107": {
    "side": "free_people",
    "twilight": 1,
    "culture": "Shire",
    "title": "Not Feared in Sunlight",
    "type": "condition",
    "keyword": "Support Area"
  },
  "2_100": {
    "side": "free_people",
    "twilight": 0,
    "culture": "Shire",
    "title": "Fearing the Worst",
    "type": "condition",
    "keyword": [
      "Support Area",
      "Stealth"
    ]
  },
  "2_111": {
    "side": "free_people",
    "twilight": 0,
    "culture": "Shire",
    "title": "Practically Everyone Was Invited",
    "type": "event",
    "keyword": "Fellowship"
  },
  "2_101": {
    "side": "free_people",
    "twilight": 1,
    "race": "Hobbit",
    "strength": 1,
    "culture": "Shire",
    "vitality": 2,
    "subtitle": "Wily Rascal",
    "title": "*Filibert Bolger",
    "type": "ally",
    "keyword": "Support Area",
    "allyHome": "Fellowship,1"
  },
  "2_112": {
    "side": "free_people",
    "twilight": 0,
    "culture": "Shire",
    "title": "A Promise",
    "type": "condition",
    "keyword": "Support Area"
  },
  "2_102": {
    "side": "free_people",
    "twilight": 0,
    "race": "Hobbit",
    "strength": 3,
    "culture": "Shire",
    "vitality": 4,
    "subtitle": "Reluctant Adventurer",
    "signet": "aragorn",
    "title": "*Frodo",
    "type": "companion",
    "keyword": "Can-bear-ring",
    "resistance": 10
  },
  "2_113": {
    "side": "free_people",
    "twilight": 2,
    "culture": "Shire",
    "title": "*Red Book of Westmarch",
    "type": "possession",
    "keyword": [
      "Support Area",
      "Tale"
    ]
  },
  "2_103": {
    "side": "free_people",
    "twilight": 0,
    "culture": "Shire",
    "title": "Hobbit Sword-play",
    "type": "event",
    "keyword": "Maneuver"
  },
  "2_114": {
    "side": "free_people",
    "twilight": 2,
    "race": "Hobbit",
    "strength": 3,
    "culture": "Shire",
    "vitality": 4,
    "subtitle": "Proper Poet",
    "signet": "gandalf",
    "title": "*Sam",
    "type": "companion",
    "resistance": 5
  },
  "2_110": {
    "side": "free_people",
    "twilight": 1,
    "race": "Hobbit",
    "strength": 3,
    "culture": "Shire",
    "vitality": 4,
    "subtitle": "Mr. Took",
    "signet": "aragorn",
    "title": "*Pippin",
    "type": "companion",
    "resistance": 6
  },
  "2_96": {
    "side": "free_people",
    "twilight": 2,
    "race": "Hobbit",
    "strength": 2,
    "culture": "Shire",
    "vitality": 3,
    "subtitle": "Well-spoken Gentlehobbit",
    "title": "*Bilbo",
    "type": "ally",
    "keyword": "Support Area",
    "allyHome": "Fellowship,1"
  },
  "2_97": {
    "side": "free_people",
    "twilight": 0,
    "culture": "Shire",
    "title": "Consorting With Wizards",
    "type": "condition",
    "keyword": "Tale"
  },
  "2_98": {
    "side": "free_people",
    "twilight": 0,
    "culture": "Shire",
    "title": "Dear Friends",
    "type": "event",
    "keyword": "Fellowship"
  },
  "2_99": {
    "side": "free_people",
    "twilight": 0,
    "culture": "Shire",
    "title": "Deft in Their Movements",
    "type": "event",
    "keyword": [
      "Regroup",
      "Stealth"
    ]
  }
}