{
  "12_51": {
    "side": "free_people",
    "cost": 1,
    "culture": "Gondor",
    "title": "Invigorated",
    "type": "condition",
    "keyword": "Support Area"
  },
  "12_52": {
    "side": "free_people",
    "cost": 1,
    "culture": "Gondor",
    "title": "Tireless",
    "type": "condition",
    "keyword": "Support Area"
  },
  "12_50": {
    "side": "free_people",
    "cost": 4,
    "culture": "Gondor",
    "title": "Guardian",
    "type": "condition",
    "keyword": [
      "Support Area",
      "Toil+2"
    ]
  },
  "12_44": {
    "side": "free_people",
    "cost": 0,
    "culture": "Gondor",
    "title": "Concealment",
    "type": "event",
    "keyword": "Skirmish"
  },
  "12_45": {
    "side": "free_people",
    "cost": 1,
    "culture": "Gondor",
    "title": "Confronting the Eye",
    "type": "condition",
    "keyword": "Support Area"
  },
  "12_42": {
    "side": "free_people",
    "cost": 1,
    "strength": 2,
    "culture": "Gondor",
    "subtitle": "Sword of Boromir",
    "itemclass": "Hand Weapon",
    "title": "*Blade of Gondor",
    "type": "possession"
  },
  "12_53": {
    "side": "free_people",
    "cost": 2,
    "culture": "Gondor",
    "title": "Valorous Leader",
    "type": "condition"
  },
  "12_48": {
    "side": "free_people",
    "cost": 2,
    "strength": 2,
    "culture": "Gondor",
    "itemclass": "Hand Weapon",
    "title": "*Faramir's Sword",
    "type": "possession"
  },
  "12_49": {
    "side": "free_people",
    "cost": 1,
    "strength": 1,
    "culture": "Gondor",
    "itemclass": "Mount",
    "title": "Gondorian Steed",
    "type": "possession",
    "resistance": 1
  },
  "12_47": {
    "side": "free_people",
    "cost": 3,
    "race": "Man",
    "strength": 7,
    "culture": "Gondor",
    "vitality": 3,
    "subtitle": "Dunadan of Gondor",
    "title": "*Faramir",
    "type": "companion",
    "keyword": "Ranger",
    "resistance": 7
  }
}